ipcl_python.libs/libssl-10f1c887.so.1.1
ipcl_python.libs/libcrypto-36d73070.so.1.1
ipcl_python-2.0.0.dist-info/RECORD
ipcl_python-2.0.0.dist-info/WHEEL
ipcl_python-2.0.0.dist-info/LICENSE
ipcl_python-2.0.0.dist-info/top_level.txt
ipcl_python-2.0.0.dist-info/METADATA
ipcl_python/__init__.py
ipcl_python/ipcl_python.py
ipcl_python/bindings/fixedpoint.py
ipcl_python/bindings/libipcl.so
ipcl_python/bindings/__init__.py
ipcl_python/bindings/libipcl.so.2.0.0
ipcl_python/bindings/ipcl_bindings.cpython-38-x86_64-linux-gnu.so
ipcl_python/bindings/cpufeatures/libcpu_features.a
ipcl_python/bindings/cpufeatures/cmake/CpuFeatures/CpuFeaturesTargets.cmake
ipcl_python/bindings/cpufeatures/cmake/CpuFeatures/CpuFeaturesTargets-release.cmake
ipcl_python/bindings/cpufeatures/cmake/CpuFeatures/CpuFeaturesConfig.cmake
ipcl_python/bindings/cpufeatures/cmake/CpuFeatures/CpuFeaturesConfigVersion.cmake
ipcl_python/bindings/ippcrypto/libcrypto_mb.so.11
ipcl_python/bindings/ippcrypto/libcrypto_mb.so
ipcl_python/bindings/ippcrypto/libippcp.so.11
ipcl_python/bindings/ippcrypto/libippcp.a
ipcl_python/bindings/ippcrypto/libippcp.so
ipcl_python/bindings/ippcrypto/libcrypto_mb.a
ipcl_python/bindings/ippcrypto/libippcp.so.11.4
ipcl_python/bindings/ippcrypto/libcrypto_mb.so.11.4
