Metadata-Version: 2.1
Name: ipcl-python
Version: 2.0.0
Summary: Python wrapper for Intel Paillier Cryptosystem Library
Author: Sejun Kim
Author-email: sejun.kim@intel.com
License: Apache-2.0
Classifier: Programming Language :: Python :: 3
Classifier: Operating System :: POSIX :: Linux
License-File: LICENSE
Requires-Dist: wheel
Requires-Dist: numpy (==1.23.1)
Requires-Dist: pycryptodomex (==3.15.0)
Requires-Dist: gmpy2 (==2.0.8)
Requires-Dist: cachetools (==3.0.0)
Requires-Dist: ruamel.yaml (==0.16.10)
